{"paging":{"pageIndex":1,"pageSize":500,"total":101},"baseComponent":{"id":"AYR86VJDLD1H3z0VTTBA","key":"fga-eps-mds_2022-2-CAPJu-Interface","name":"2022-2-CAPJu-Interface","qualifier":"TRK","measures":[{"metric":"duplicated_lines_density","value":"3.5","bestValue":false},{"metric":"functions","value":"247"},{"metric":"security_rating","value":"1.0","bestValue":true},{"metric":"files","value":"59"},{"metric":"complexity","value":"419"},{"metric":"ncloc","value":"5076"},{"metric":"coverage","value":"72.4","bestValue":false},{"metric":"comment_lines_density","value":"0.4","bestValue":false}]},"components":[{"id":"AYSQtNBWIoqdY8fpFmYb","key":"fga-eps-mds_2022-2-CAPJu-Interface:src/__tests__","name":"__tests__","qualifier":"DIR","path":"src/__tests__","measures":[{"metric":"security_rating","value":"1.0","bestValue":true}]},{"id":"AYSQtNBVIoqdY8fpFmYA","key":"fga-eps-mds_2022-2-CAPJu-Interface:src/pages/AccessProfile","name":"AccessProfile","qualifier":"DIR","path":"src/pages/AccessProfile","measures":[{"metric":"duplicated_lines_density","value":"0.0","bestValue":true},{"metric":"functions","value":"21"},{"metric":"security_rating","value":"1.0","bestValue":true},{"metric":"files","value":"2"},{"metric":"complexity","value":"31"},{"metric":"ncloc","value":"309"},{"metric":"coverage","value":"100.0","bestValue":true},{"metric":"comment_lines_density","value":"0.3","bestValue":false}]},{"id":"AYSQtNBVIoqdY8fpFmX-","key":"fga-eps-mds_2022-2-CAPJu-Interface:src/pages/AccessProfile/AccessProfile.jsx","name":"AccessProfile.jsx","qualifier":"FIL","path":"src/pages/AccessProfile/AccessProfile.jsx","language":"js","measures":[{"metric":"complexity","value":"31"},{"metric":"functions","value":"21"},{"metric":"ncloc","value":"231"},{"metric":"coverage","value":"100.0","bestValue":true},{"metric":"security_rating","value":"1.0","bestValue":true},{"metric":"comment_lines_density","value":"0.4","bestValue":false},{"metric":"files","value":"1"},{"metric":"test_errors","value":"0","bestValue":true},{"metric":"duplicated_lines_density","value":"0.0","bestValue":true},{"metric":"test_failures","value":"0","bestValue":true}]},{"id":"AYSQtNBVIoqdY8fpFmXQ","key":"fga-eps-mds_2022-2-CAPJu-Interface:src/components/AddSequenceInFlow","name":"AddSequenceInFlow","qualifier":"DIR","path":"src/components/AddSequenceInFlow","measures":[{"metric":"duplicated_lines_density","value":"0.0","bestValue":true},{"metric":"functions","value":"2"},{"metric":"security_rating","value":"1.0","bestValue":true},{"metric":"files","value":"1"},{"metric":"complexity","value":"2"},{"metric":"ncloc","value":"27"},{"metric":"coverage","value":"100.0","bestValue":true},{"metric":"comment_lines_density","value":"0.0","bestValue":false}]},{"id":"AYSQtNBVIoqdY8fpFmXP","key":"fga-eps-mds_2022-2-CAPJu-Interface:src/components/AddSequenceInFlow/AddSequenceInFlow.jsx","name":"AddSequenceInFlow.jsx","qualifier":"FIL","path":"src/components/AddSequenceInFlow/AddSequenceInFlow.jsx","language":"js","measures":[{"metric":"complexity","value":"2"},{"metric":"functions","value":"2"},{"metric":"ncloc","value":"27"},{"metric":"coverage","value":"100.0","bestValue":true},{"metric":"security_rating","value":"1.0","bestValue":true},{"metric":"comment_lines_density","value":"0.0","bestValue":false},{"metric":"files","value":"1"},{"metric":"test_errors","value":"0","bestValue":true},{"metric":"duplicated_lines_density","value":"0.0","bestValue":true},{"metric":"test_failures","value":"0","bestValue":true}]},{"id":"AYSQtNBVIoqdY8fpFmXh","key":"fga-eps-mds_2022-2-CAPJu-Interface:src/components/AddStageInFlow","name":"AddStageInFlow","qualifier":"DIR","path":"src/components/AddStageInFlow","measures":[{"metric":"duplicated_lines_density","value":"0.0","bestValue":true},{"metric":"functions","value":"3"},{"metric":"security_rating","value":"1.0","bestValue":true},{"metric":"files","value":"2"},{"metric":"complexity","value":"3"},{"metric":"ncloc","value":"54"},{"metric":"coverage","value":"100.0","bestValue":true},{"metric":"comment_lines_density","value":"0.0","bestValue":false}]},{"id":"AYSQtNBVIoqdY8fpFmXg","key":"fga-eps-mds_2022-2-CAPJu-Interface:src/components/AddStageInFlow/AddStageInFlow.jsx","name":"AddStageInFlow.jsx","qualifier":"FIL","path":"src/components/AddStageInFlow/AddStageInFlow.jsx","language":"js","measures":[{"metric":"complexity","value":"3"},{"metric":"functions","value":"3"},{"metric":"ncloc","value":"38"},{"metric":"coverage","value":"100.0","bestValue":true},{"metric":"security_rating","value":"1.0","bestValue":true},{"metric":"comment_lines_density","value":"0.0","bestValue":false},{"metric":"files","value":"1"},{"metric":"test_errors","value":"0","bestValue":true},{"metric":"duplicated_lines_density","value":"0.0","bestValue":true},{"metric":"test_failures","value":"0","bestValue":true}]},{"id":"AYSQtNBWIoqdY8fpFmYO","key":"fga-eps-mds_2022-2-CAPJu-Interface:src/services/api.js","name":"api.js","qualifier":"FIL","path":"src/services/api.js","language":"js","measures":[{"metric":"complexity","value":"1"},{"metric":"functions","value":"0"},{"metric":"ncloc","value":"10"},{"metric":"coverage","value":"75.0","bestValue":false},{"metric":"security_rating","value":"1.0","bestValue":true},{"metric":"comment_lines_density","value":"0.0","bestValue":false},{"metric":"files","value":"1"},{"metric":"test_errors","value":"0","bestValue":true},{"metric":"duplicated_lines_density","value":"0.0","bestValue":true},{"metric":"test_failures","value":"0","bestValue":true}]},{"id":"AYSQtNBWIoqdY8fpFmYi","key":"fga-eps-mds_2022-2-CAPJu-Interface:src/App.js","name":"App.js","qualifier":"FIL","path":"src/App.js","language":"js","measures":[{"metric":"complexity","value":"8"},{"metric":"functions","value":"2"},{"metric":"ncloc","value":"77"},{"metric":"coverage","value":"0.0","bestValue":false},{"metric":"security_rating","value":"1.0","bestValue":true},{"metric":"comment_lines_density","value":"0.0","bestValue":false},{"metric":"files","value":"1"},{"metric":"test_errors","value":"0","bestValue":true},{"metric":"duplicated_lines_density","value":"0.0","bestValue":true},{"metric":"test_failures","value":"0","bestValue":true}]},{"id":"AYWhUJA5qQu-3RSfafYl","key":"fga-eps-mds_2022-2-CAPJu-Interface:src/components/BackButton","name":"BackButton","qualifier":"DIR","path":"src/components/BackButton","measures":[{"metric":"duplicated_lines_density","value":"0.0","bestValue":true},{"metric":"functions","value":"3"},{"metric":"security_rating","value":"1.0","bestValue":true},{"metric":"files","value":"2"},{"metric":"complexity","value":"3"},{"metric":"ncloc","value":"22"},{"metric":"coverage","value":"85.7","bestValue":false},{"metric":"comment_lines_density","value":"0.0","bestValue":false}]},{"id":"AYWhUJA5qQu-3RSfafYj","key":"fga-eps-mds_2022-2-CAPJu-Interface:src/components/BackButton/BackButton.jsx","name":"BackButton.jsx","qualifier":"FIL","path":"src/components/BackButton/BackButton.jsx","language":"js","measures":[{"metric":"complexity","value":"2"},{"metric":"functions","value":"2"},{"metric":"ncloc","value":"12"},{"metric":"coverage","value":"83.3","bestValue":false},{"metric":"security_rating","value":"1.0","bestValue":true},{"metric":"comment_lines_density","value":"0.0","bestValue":false},{"metric":"files","value":"1"},{"metric":"test_errors","value":"0","bestValue":true},{"metric":"duplicated_lines_density","value":"0.0","bestValue":true},{"metric":"test_failures","value":"0","bestValue":true}]},{"id":"AYSQtNBVIoqdY8fpFmXI","key":"fga-eps-mds_2022-2-CAPJu-Interface:src/components/Button","name":"Button","qualifier":"DIR","path":"src/components/Button","measures":[{"metric":"duplicated_lines_density","value":"0.0","bestValue":true},{"metric":"functions","value":"5"},{"metric":"security_rating","value":"1.0","bestValue":true},{"metric":"files","value":"2"},{"metric":"complexity","value":"9"},{"metric":"ncloc","value":"97"},{"metric":"coverage","value":"100.0","bestValue":true},{"metric":"comment_lines_density","value":"0.0","bestValue":false}]},{"id":"AYSQtNBVIoqdY8fpFmXH","key":"fga-eps-mds_2022-2-CAPJu-Interface:src/components/Button/Button.jsx","name":"Button.jsx","qualifier":"FIL","path":"src/components/Button/Button.jsx","language":"js","measures":[{"metric":"complexity","value":"2"},{"metric":"functions","value":"1"},{"metric":"ncloc","value":"26"},{"metric":"coverage","value":"100.0","bestValue":true},{"metric":"security_rating","value":"1.0","bestValue":true},{"metric":"comment_lines_density","value":"0.0","bestValue":false},{"metric":"files","value":"1"},{"metric":"test_errors","value":"0","bestValue":true},{"metric":"duplicated_lines_density","value":"0.0","bestValue":true},{"metric":"test_failures","value":"0","bestValue":true}]},{"id":"AYSQtNBVIoqdY8fpFmXi","key":"fga-eps-mds_2022-2-CAPJu-Interface:src/components","name":"components","qualifier":"DIR","path":"src/components","measures":[{"metric":"duplicated_lines_density","value":"0.0","bestValue":true},{"metric":"functions","value":"45"},{"metric":"security_rating","value":"1.0","bestValue":true},{"metric":"files","value":"23"},{"metric":"complexity","value":"73"},{"metric":"ncloc","value":"931"},{"metric":"coverage","value":"80.2","bestValue":false},{"metric":"comment_lines_density","value":"0.1","bestValue":false}]},{"id":"AYSQtNBWIoqdY8fpFmYP","key":"fga-eps-mds_2022-2-CAPJu-Interface:src/services/config.js","name":"config.js","qualifier":"FIL","path":"src/services/config.js","language":"js","measures":[{"metric":"complexity","value":"1"},{"metric":"functions","value":"1"},{"metric":"ncloc","value":"10"},{"metric":"coverage","value":"0.0","bestValue":false},{"metric":"security_rating","value":"1.0","bestValue":true},{"metric":"comment_lines_density","value":"0.0","bestValue":false},{"metric":"files","value":"1"},{"metric":"test_errors","value":"0","bestValue":true},{"metric":"duplicated_lines_density","value":"0.0","bestValue":true},{"metric":"test_failures","value":"0","bestValue":true}]},{"id":"AYWhUJA5qQu-3RSfafYp","key":"fga-eps-mds_2022-2-CAPJu-Interface:src/validators/cpfValidator.js","name":"cpfValidator.js","qualifier":"FIL","path":"src/validators/cpfValidator.js","language":"js","measures":[{"metric":"files","value":"1"},{"metric":"ncloc","value":"34"},{"metric":"coverage","value":"0.0","bestValue":false},{"metric":"functions","value":"1"},{"metric":"complexity","value":"10"},{"metric":"security_rating","value":"1.0","bestValue":true},{"metric":"comment_lines_density","value":"0.0","bestValue":false},{"metric":"duplicated_lines_density","value":"95.1","bestValue":false},{"metric":"test_errors","value":"0","bestValue":true},{"metric":"test_failures","value":"0","bestValue":true}]},{"id":"AYWhUJA5qQu-3RSfafYf","key":"fga-eps-mds_2022-2-CAPJu-Interface:src/components/FlowViewer/EdgeButton.jsx","name":"EdgeButton.jsx","qualifier":"FIL","path":"src/components/FlowViewer/EdgeButton.jsx","language":"js","measures":[{"metric":"complexity","value":"4"},{"metric":"functions","value":"2"},{"metric":"ncloc","value":"93"},{"metric":"coverage","value":"11.8","bestValue":false},{"metric":"security_rating","value":"1.0","bestValue":true},{"metric":"comment_lines_density","value":"0.0","bestValue":false},{"metric":"files","value":"1"},{"metric":"test_errors","value":"0","bestValue":true},{"metric":"duplicated_lines_density","value":"0.0","bestValue":true},{"metric":"test_failures","value":"0","bestValue":true}]},{"id":"AYSQtNBWIoqdY8fpFmYM","key":"fga-eps-mds_2022-2-CAPJu-Interface:src/pages/EditAccount","name":"EditAccount","qualifier":"DIR","path":"src/pages/EditAccount","measures":[{"metric":"duplicated_lines_density","value":"0.0","bestValue":true},{"metric":"functions","value":"1"},{"metric":"security_rating","value":"1.0","bestValue":true},{"metric":"files","value":"2"},{"metric":"complexity","value":"1"},{"metric":"ncloc","value":"67"},{"metric":"coverage","value":"71.4","bestValue":false},{"metric":"comment_lines_density","value":"0.0","bestValue":false}]},{"id":"AYSQtNBWIoqdY8fpFmYL","key":"fga-eps-mds_2022-2-CAPJu-Interface:src/pages/EditAccount/EditAccount.jsx","name":"EditAccount.jsx","qualifier":"FIL","path":"src/pages/EditAccount/EditAccount.jsx","language":"js","measures":[{"metric":"complexity","value":"1"},{"metric":"functions","value":"1"},{"metric":"ncloc","value":"31"},{"metric":"coverage","value":"0.0","bestValue":false},{"metric":"security_rating","value":"1.0","bestValue":true},{"metric":"comment_lines_density","value":"0.0","bestValue":false},{"metric":"files","value":"1"},{"metric":"test_errors","value":"0","bestValue":true},{"metric":"duplicated_lines_density","value":"0.0","bestValue":true},{"metric":"test_failures","value":"0","bestValue":true}]},{"id":"AYSQtNBVIoqdY8fpFmXo","key":"fga-eps-mds_2022-2-CAPJu-Interface:src/pages/EditAccountEmail","name":"EditAccountEmail","qualifier":"DIR","path":"src/pages/EditAccountEmail","measures":[{"metric":"duplicated_lines_density","value":"0.0","bestValue":true},{"metric":"functions","value":"3"},{"metric":"security_rating","value":"1.0","bestValue":true},{"metric":"files","value":"2"},{"metric":"complexity","value":"6"},{"metric":"ncloc","value":"119"},{"metric":"coverage","value":"79.3","bestValue":false},{"metric":"comment_lines_density","value":"0.0","bestValue":false}]},{"id":"AYSQtNBVIoqdY8fpFmXn","key":"fga-eps-mds_2022-2-CAPJu-Interface:src/pages/EditAccountEmail/EditAccountEmail.jsx","name":"EditAccountEmail.jsx","qualifier":"FIL","path":"src/pages/EditAccountEmail/EditAccountEmail.jsx","language":"js","measures":[{"metric":"complexity","value":"6"},{"metric":"functions","value":"3"},{"metric":"ncloc","value":"75"},{"metric":"coverage","value":"75.0","bestValue":false},{"metric":"security_rating","value":"1.0","bestValue":true},{"metric":"comment_lines_density","value":"0.0","bestValue":false},{"metric":"files","value":"1"},{"metric":"test_errors","value":"0","bestValue":true},{"metric":"duplicated_lines_density","value":"0.0","bestValue":true},{"metric":"test_failures","value":"0","bestValue":true}]},{"id":"AYSQtNBVIoqdY8fpFmXr","key":"fga-eps-mds_2022-2-CAPJu-Interface:src/pages/EditAccountPassword","name":"EditAccountPassword","qualifier":"DIR","path":"src/pages/EditAccountPassword","measures":[{"metric":"duplicated_lines_density","value":"0.0","bestValue":true},{"metric":"functions","value":"3"},{"metric":"security_rating","value":"1.0","bestValue":true},{"metric":"files","value":"2"},{"metric":"complexity","value":"5"},{"metric":"ncloc","value":"134"},{"metric":"coverage","value":"76.7","bestValue":false},{"metric":"comment_lines_density","value":"0.0","bestValue":false}]},{"id":"AYSQtNBVIoqdY8fpFmXp","key":"fga-eps-mds_2022-2-CAPJu-Interface:src/pages/EditAccountPassword/EditAccountPassword.jsx","name":"EditAccountPassword.jsx","qualifier":"FIL","path":"src/pages/EditAccountPassword/EditAccountPassword.jsx","language":"js","measures":[{"metric":"complexity","value":"5"},{"metric":"functions","value":"3"},{"metric":"ncloc","value":"90"},{"metric":"coverage","value":"72.0","bestValue":false},{"metric":"security_rating","value":"1.0","bestValue":true},{"metric":"comment_lines_density","value":"0.0","bestValue":false},{"metric":"files","value":"1"},{"metric":"test_errors","value":"0","bestValue":true},{"metric":"duplicated_lines_density","value":"0.0","bestValue":true},{"metric":"test_failures","value":"0","bestValue":true}]},{"id":"AYSQtNBVIoqdY8fpFmX0","key":"fga-eps-mds_2022-2-CAPJu-Interface:src/pages/Flows","name":"Flows","qualifier":"DIR","path":"src/pages/Flows","measures":[{"metric":"duplicated_lines_density","value":"0.0","bestValue":true},{"metric":"functions","value":"31"},{"metric":"security_rating","value":"1.0","bestValue":true},{"metric":"files","value":"2"},{"metric":"complexity","value":"44"},{"metric":"ncloc","value":"658"},{"metric":"coverage","value":"80.7","bestValue":false},{"metric":"comment_lines_density","value":"1.3","bestValue":false}]},{"id":"AYSQtNBVIoqdY8fpFmXz","key":"fga-eps-mds_2022-2-CAPJu-Interface:src/pages/Flows/Flows.jsx","name":"Flows.jsx","qualifier":"FIL","path":"src/pages/Flows/Flows.jsx","language":"js","measures":[{"metric":"complexity","value":"44"},{"metric":"functions","value":"31"},{"metric":"ncloc","value":"437"},{"metric":"coverage","value":"78.2","bestValue":false},{"metric":"security_rating","value":"1.0","bestValue":true},{"metric":"comment_lines_density","value":"2.0","bestValue":false},{"metric":"files","value":"1"},{"metric":"test_errors","value":"0","bestValue":true},{"metric":"duplicated_lines_density","value":"0.0","bestValue":true},{"metric":"test_failures","value":"0","bestValue":true}]},{"id":"AYSQtNBVIoqdY8fpFmXe","key":"fga-eps-mds_2022-2-CAPJu-Interface:src/components/FlowViewer","name":"FlowViewer","qualifier":"DIR","path":"src/components/FlowViewer","measures":[{"metric":"duplicated_lines_density","value":"0.0","bestValue":true},{"metric":"functions","value":"10"},{"metric":"security_rating","value":"1.0","bestValue":true},{"metric":"files","value":"3"},{"metric":"complexity","value":"28"},{"metric":"ncloc","value":"249"},{"metric":"coverage","value":"67.1","bestValue":false},{"metric":"comment_lines_density","value":"0.0","bestValue":false}]},{"id":"AYSQtNBVIoqdY8fpFmXd","key":"fga-eps-mds_2022-2-CAPJu-Interface:src/components/FlowViewer/FlowViewer.jsx","name":"FlowViewer.jsx","qualifier":"FIL","path":"src/components/FlowViewer/FlowViewer.jsx","language":"js","measures":[{"metric":"functions","value":"8"},{"metric":"security_rating","value":"1.0","bestValue":true},{"metric":"files","value":"1"},{"metric":"complexity","value":"24"},{"metric":"ncloc","value":"119"},{"metric":"coverage","value":"80.0","bestValue":false},{"metric":"comment_lines_density","value":"0.0","bestValue":false},{"metric":"test_errors","value":"0","bestValue":true},{"metric":"duplicated_lines_density","value":"0.0","bestValue":true},{"metric":"test_failures","value":"0","bestValue":true}]},{"id":"AYSQtNBWIoqdY8fpFmYe","key":"fga-eps-mds_2022-2-CAPJu-Interface:src/globalStyles.js","name":"globalStyles.js","qualifier":"FIL","path":"src/globalStyles.js","language":"js","measures":[{"metric":"complexity","value":"0"},{"metric":"functions","value":"0"},{"metric":"ncloc","value":"63"},{"metric":"coverage","value":"100.0","bestValue":true},{"metric":"security_rating","value":"1.0","bestValue":true},{"metric":"comment_lines_density","value":"0.0","bestValue":false},{"metric":"files","value":"1"},{"metric":"test_errors","value":"0","bestValue":true},{"metric":"duplicated_lines_density","value":"0.0","bestValue":true},{"metric":"test_failures","value":"0","bestValue":true}]},{"id":"AYSQtNBWIoqdY8fpFmYf","key":"fga-eps-mds_2022-2-CAPJu-Interface:src/index.css","name":"index.css","qualifier":"FIL","path":"src/index.css","language":"css","measures":[{"metric":"security_rating","value":"1.0","bestValue":true},{"metric":"comment_lines_density","value":"0.0","bestValue":false},{"metric":"ncloc","value":"12"},{"metric":"files","value":"1"},{"metric":"test_errors","value":"0","bestValue":true},{"metric":"duplicated_lines_density","value":"0.0","bestValue":true},{"metric":"test_failures","value":"0","bestValue":true}]},{"id":"AYSQtNBWIoqdY8fpFmYg","key":"fga-eps-mds_2022-2-CAPJu-Interface:src/index.js","name":"index.js","qualifier":"FIL","path":"src/index.js","language":"js","measures":[{"metric":"complexity","value":"0"},{"metric":"functions","value":"0"},{"metric":"ncloc","value":"13"},{"metric":"coverage","value":"0.0","bestValue":false},{"metric":"security_rating","value":"1.0","bestValue":true},{"metric":"comment_lines_density","value":"0.0","bestValue":false},{"metric":"files","value":"1"},{"metric":"test_errors","value":"0","bestValue":true},{"metric":"duplicated_lines_density","value":"0.0","bestValue":true},{"metric":"test_failures","value":"0","bestValue":true}]},{"id":"AYSQtNBVIoqdY8fpFmXa","key":"fga-eps-mds_2022-2-CAPJu-Interface:src/components/IsLate/index.js","name":"index.js","qualifier":"FIL","path":"src/components/IsLate/index.js","language":"js","measures":[{"metric":"complexity","value":"5"},{"metric":"functions","value":"3"},{"metric":"ncloc","value":"16"},{"metric":"coverage","value":"92.9","bestValue":false},{"metric":"security_rating","value":"1.0","bestValue":true},{"metric":"comment_lines_density","value":"0.0","bestValue":false},{"metric":"files","value":"1"},{"metric":"test_errors","value":"0","bestValue":true},{"metric":"duplicated_lines_density","value":"0.0","bestValue":true},{"metric":"test_failures","value":"0","bestValue":true}]},{"id":"AYSQtNBVIoqdY8fpFmXb","key":"fga-eps-mds_2022-2-CAPJu-Interface:src/components/IsLate","name":"IsLate","qualifier":"DIR","path":"src/components/IsLate","measures":[{"metric":"duplicated_lines_density","value":"0.0","bestValue":true},{"metric":"functions","value":"3"},{"metric":"security_rating","value":"1.0","bestValue":true},{"metric":"files","value":"1"},{"metric":"complexity","value":"5"},{"metric":"ncloc","value":"16"},{"metric":"coverage","value":"92.9","bestValue":false},{"metric":"comment_lines_density","value":"0.0","bestValue":false}]},{"id":"AYSQtNBVIoqdY8fpFmXl","key":"fga-eps-mds_2022-2-CAPJu-Interface:src/pages/Login","name":"Login","qualifier":"DIR","path":"src/pages/Login","measures":[{"metric":"duplicated_lines_density","value":"0.0","bestValue":true},{"metric":"functions","value":"22"},{"metric":"security_rating","value":"1.0","bestValue":true},{"metric":"files","value":"2"},{"metric":"complexity","value":"36"},{"metric":"ncloc","value":"396"},{"metric":"coverage","value":"74.0","bestValue":false},{"metric":"comment_lines_density","value":"0.8","bestValue":false}]},{"id":"AYSQtNBVIoqdY8fpFmXk","key":"fga-eps-mds_2022-2-CAPJu-Interface:src/pages/Login/Login.jsx","name":"Login.jsx","qualifier":"FIL","path":"src/pages/Login/Login.jsx","language":"js","measures":[{"metric":"functions","value":"20"},{"metric":"security_rating","value":"1.0","bestValue":true},{"metric":"files","value":"1"},{"metric":"complexity","value":"33"},{"metric":"ncloc","value":"341"},{"metric":"coverage","value":"71.7","bestValue":false},{"metric":"comment_lines_density","value":"0.9","bestValue":false},{"metric":"test_errors","value":"0","bestValue":true},{"metric":"duplicated_lines_density","value":"0.0","bestValue":true},{"metric":"test_failures","value":"0","bestValue":true}]},{"id":"AYSQtNBVIoqdY8fpFmXv","key":"fga-eps-mds_2022-2-CAPJu-Interface:src/pages/Recovery/Login.jsx","name":"Login.jsx","qualifier":"FIL","path":"src/pages/Recovery/Login.jsx","language":"js","measures":[{"metric":"complexity","value":"9"},{"metric":"functions","value":"5"},{"metric":"ncloc","value":"83"},{"metric":"coverage","value":"0.0","bestValue":false},{"metric":"security_rating","value":"1.0","bestValue":true},{"metric":"comment_lines_density","value":"0.0","bestValue":false},{"metric":"files","value":"1"},{"metric":"test_errors","value":"0","bestValue":true},{"metric":"duplicated_lines_density","value":"0.0","bestValue":true},{"metric":"test_failures","value":"0","bestValue":true}]},{"id":"AYSQtNBVIoqdY8fpFmXL","key":"fga-eps-mds_2022-2-CAPJu-Interface:src/components/ModalBody","name":"ModalBody","qualifier":"DIR","path":"src/components/ModalBody","measures":[{"metric":"duplicated_lines_density","value":"0.0","bestValue":true},{"metric":"functions","value":"1"},{"metric":"security_rating","value":"1.0","bestValue":true},{"metric":"files","value":"2"},{"metric":"complexity","value":"1"},{"metric":"ncloc","value":"22"},{"metric":"coverage","value":"100.0","bestValue":true},{"metric":"comment_lines_density","value":"0.0","bestValue":false}]},{"id":"AYSQtNBVIoqdY8fpFmXJ","key":"fga-eps-mds_2022-2-CAPJu-Interface:src/components/ModalBody/ModalBody.jsx","name":"ModalBody.jsx","qualifier":"FIL","path":"src/components/ModalBody/ModalBody.jsx","language":"js","measures":[{"metric":"complexity","value":"1"},{"metric":"functions","value":"1"},{"metric":"ncloc","value":"10"},{"metric":"coverage","value":"100.0","bestValue":true},{"metric":"security_rating","value":"1.0","bestValue":true},{"metric":"comment_lines_density","value":"0.0","bestValue":false},{"metric":"files","value":"1"},{"metric":"test_errors","value":"0","bestValue":true},{"metric":"duplicated_lines_density","value":"0.0","bestValue":true},{"metric":"test_failures","value":"0","bestValue":true}]},{"id":"AYSQtNBVIoqdY8fpFmXZ","key":"fga-eps-mds_2022-2-CAPJu-Interface:src/components/ModalHeader","name":"ModalHeader","qualifier":"DIR","path":"src/components/ModalHeader","measures":[{"metric":"duplicated_lines_density","value":"0.0","bestValue":true},{"metric":"functions","value":"1"},{"metric":"security_rating","value":"1.0","bestValue":true},{"metric":"files","value":"2"},{"metric":"complexity","value":"1"},{"metric":"ncloc","value":"49"},{"metric":"coverage","value":"100.0","bestValue":true},{"metric":"comment_lines_density","value":"0.0","bestValue":false}]},{"id":"AYSQtNBVIoqdY8fpFmXN","key":"fga-eps-mds_2022-2-CAPJu-Interface:src/components/SideBar/ModalHeader.jsx","name":"ModalHeader.jsx","qualifier":"FIL","path":"src/components/SideBar/ModalHeader.jsx","language":"js","measures":[{"metric":"complexity","value":"6"},{"metric":"functions","value":"4"},{"metric":"ncloc","value":"100"},{"metric":"coverage","value":"88.2","bestValue":false},{"metric":"security_rating","value":"1.0","bestValue":true},{"metric":"comment_lines_density","value":"1.0","bestValue":false},{"metric":"files","value":"1"},{"metric":"test_errors","value":"0","bestValue":true},{"metric":"duplicated_lines_density","value":"0.0","bestValue":true},{"metric":"test_failures","value":"0","bestValue":true}]},{"id":"AYSQtNBVIoqdY8fpFmXX","key":"fga-eps-mds_2022-2-CAPJu-Interface:src/components/ModalHeader/ModalHeader.jsx","name":"ModalHeader.jsx","qualifier":"FIL","path":"src/components/ModalHeader/ModalHeader.jsx","language":"js","measures":[{"metric":"complexity","value":"1"},{"metric":"functions","value":"1"},{"metric":"ncloc","value":"16"},{"metric":"coverage","value":"100.0","bestValue":true},{"metric":"security_rating","value":"1.0","bestValue":true},{"metric":"comment_lines_density","value":"0.0","bestValue":false},{"metric":"files","value":"1"},{"metric":"test_errors","value":"0","bestValue":true},{"metric":"duplicated_lines_density","value":"0.0","bestValue":true},{"metric":"test_failures","value":"0","bestValue":true}]},{"id":"AYSQtNBWIoqdY8fpFmYN","key":"fga-eps-mds_2022-2-CAPJu-Interface:src/pages","name":"pages","qualifier":"DIR","path":"src/pages","measures":[{"metric":"duplicated_lines_density","value":"0.9","bestValue":false},{"metric":"functions","value":"190"},{"metric":"security_rating","value":"1.0","bestValue":true},{"metric":"files","value":"24"},{"metric":"complexity","value":"306"},{"metric":"ncloc","value":"3557"},{"metric":"coverage","value":"75.4","bestValue":false},{"metric":"comment_lines_density","value":"0.5","bestValue":false}]},{"id":"AYSQtNBVIoqdY8fpFmXu","key":"fga-eps-mds_2022-2-CAPJu-Interface:src/pages/Processes","name":"Processes","qualifier":"DIR","path":"src/pages/Processes","measures":[{"metric":"duplicated_lines_density","value":"0.0","bestValue":true},{"metric":"functions","value":"26"},{"metric":"security_rating","value":"1.0","bestValue":true},{"metric":"files","value":"2"},{"metric":"complexity","value":"52"},{"metric":"ncloc","value":"537"},{"metric":"coverage","value":"84.1","bestValue":false},{"metric":"comment_lines_density","value":"0.6","bestValue":false}]},{"id":"AYSQtNBVIoqdY8fpFmXt","key":"fga-eps-mds_2022-2-CAPJu-Interface:src/pages/Processes/Processes.jsx","name":"Processes.jsx","qualifier":"FIL","path":"src/pages/Processes/Processes.jsx","language":"js","measures":[{"metric":"functions","value":"26"},{"metric":"security_rating","value":"1.0","bestValue":true},{"metric":"files","value":"1"},{"metric":"complexity","value":"52"},{"metric":"ncloc","value":"350"},{"metric":"coverage","value":"83.3","bestValue":false},{"metric":"comment_lines_density","value":"0.8","bestValue":false},{"metric":"test_errors","value":"0","bestValue":true},{"metric":"duplicated_lines_density","value":"0.0","bestValue":true},{"metric":"test_failures","value":"0","bestValue":true}]},{"id":"AYSQtNBVIoqdY8fpFmXx","key":"fga-eps-mds_2022-2-CAPJu-Interface:src/pages/Recovery","name":"Recovery","qualifier":"DIR","path":"src/pages/Recovery","measures":[{"metric":"duplicated_lines_density","value":"0.0","bestValue":true},{"metric":"functions","value":"7"},{"metric":"security_rating","value":"1.0","bestValue":true},{"metric":"files","value":"2"},{"metric":"complexity","value":"12"},{"metric":"ncloc","value":"126"},{"metric":"coverage","value":"13.5","bestValue":false},{"metric":"comment_lines_density","value":"0.0","bestValue":false}]},{"id":"AYWhUJA5qQu-3RSfafYq","key":"fga-eps-mds_2022-2-CAPJu-Interface:src/validators/registryValidator.js","name":"registryValidator.js","qualifier":"FIL","path":"src/validators/registryValidator.js","language":"js","measures":[{"metric":"files","value":"1"},{"metric":"ncloc","value":"43"},{"metric":"coverage","value":"78.4","bestValue":false},{"metric":"functions","value":"2"},{"metric":"complexity","value":"12"},{"metric":"security_rating","value":"1.0","bestValue":true},{"metric":"comment_lines_density","value":"0.0","bestValue":false},{"metric":"duplicated_lines_density","value":"76.5","bestValue":false},{"metric":"test_errors","value":"0","bestValue":true},{"metric":"test_failures","value":"0","bestValue":true}]},{"id":"AYSQtNBWIoqdY8fpFmYR","key":"fga-eps-mds_2022-2-CAPJu-Interface:src/services","name":"services","qualifier":"DIR","path":"src/services","measures":[{"metric":"duplicated_lines_density","value":"0.0","bestValue":true},{"metric":"functions","value":"1"},{"metric":"security_rating","value":"1.0","bestValue":true},{"metric":"files","value":"3"},{"metric":"complexity","value":"3"},{"metric":"ncloc","value":"30"},{"metric":"coverage","value":"54.5","bestValue":false},{"metric":"comment_lines_density","value":"0.0","bestValue":false}]},{"id":"AYSQtNBWIoqdY8fpFmYd","key":"fga-eps-mds_2022-2-CAPJu-Interface:src/setupTests.js","name":"setupTests.js","qualifier":"FIL","path":"src/setupTests.js","language":"js","measures":[{"metric":"complexity","value":"7"},{"metric":"functions","value":"6"},{"metric":"ncloc","value":"25"},{"metric":"coverage","value":"0.0","bestValue":false},{"metric":"security_rating","value":"1.0","bestValue":true},{"metric":"comment_lines_density","value":"0.0","bestValue":false},{"metric":"files","value":"1"},{"metric":"test_errors","value":"0","bestValue":true},{"metric":"duplicated_lines_density","value":"0.0","bestValue":true},{"metric":"test_failures","value":"0","bestValue":true}]},{"id":"AYSQtNBVIoqdY8fpFmX9","key":"fga-eps-mds_2022-2-CAPJu-Interface:src/pages/ShowProcess","name":"ShowProcess","qualifier":"DIR","path":"src/pages/ShowProcess","measures":[{"metric":"duplicated_lines_density","value":"0.0","bestValue":true},{"metric":"functions","value":"29"},{"metric":"security_rating","value":"1.0","bestValue":true},{"metric":"files","value":"2"},{"metric":"complexity","value":"43"},{"metric":"ncloc","value":"355"},{"metric":"coverage","value":"63.0","bestValue":false},{"metric":"comment_lines_density","value":"0.6","bestValue":false}]},{"id":"AYSQtNBVIoqdY8fpFmX8","key":"fga-eps-mds_2022-2-CAPJu-Interface:src/pages/ShowProcess/ShowProcess.jsx","name":"ShowProcess.jsx","qualifier":"FIL","path":"src/pages/ShowProcess/ShowProcess.jsx","language":"js","measures":[{"metric":"functions","value":"29"},{"metric":"security_rating","value":"1.0","bestValue":true},{"metric":"files","value":"1"},{"metric":"complexity","value":"43"},{"metric":"ncloc","value":"306"},{"metric":"coverage","value":"62.4","bestValue":false},{"metric":"comment_lines_density","value":"0.6","bestValue":false},{"metric":"test_errors","value":"0","bestValue":true},{"metric":"duplicated_lines_density","value":"0.0","bestValue":true},{"metric":"test_failures","value":"0","bestValue":true}]},{"id":"AYSQtNBVIoqdY8fpFmXO","key":"fga-eps-mds_2022-2-CAPJu-Interface:src/components/SideBar","name":"SideBar","qualifier":"DIR","path":"src/components/SideBar","measures":[{"metric":"duplicated_lines_density","value":"0.0","bestValue":true},{"metric":"functions","value":"4"},{"metric":"security_rating","value":"1.0","bestValue":true},{"metric":"files","value":"2"},{"metric":"complexity","value":"6"},{"metric":"ncloc","value":"164"},{"metric":"coverage","value":"90.9","bestValue":false},{"metric":"comment_lines_density","value":"0.6","bestValue":false}]},{"id":"AYSQtNBWIoqdY8fpFmYJ","key":"fga-eps-mds_2022-2-CAPJu-Interface:src/pages/SolicitacoesCadastro","name":"SolicitacoesCadastro","qualifier":"DIR","path":"src/pages/SolicitacoesCadastro","measures":[{"metric":"duplicated_lines_density","value":"13.4","bestValue":false},{"metric":"functions","value":"14"},{"metric":"security_rating","value":"1.0","bestValue":true},{"metric":"files","value":"2"},{"metric":"complexity","value":"24"},{"metric":"ncloc","value":"249"},{"metric":"coverage","value":"78.9","bestValue":false},{"metric":"comment_lines_density","value":"0.4","bestValue":false}]},{"id":"AYSQtNBWIoqdY8fpFmYH","key":"fga-eps-mds_2022-2-CAPJu-Interface:src/pages/SolicitacoesCadastro/SolicitacoesCadastro.jsx","name":"SolicitacoesCadastro.jsx","qualifier":"FIL","path":"src/pages/SolicitacoesCadastro/SolicitacoesCadastro.jsx","language":"js","measures":[{"metric":"files","value":"1"},{"metric":"ncloc","value":"175"},{"metric":"coverage","value":"77.5","bestValue":false},{"metric":"functions","value":"14"},{"metric":"complexity","value":"24"},{"metric":"security_rating","value":"1.0","bestValue":true},{"metric":"comment_lines_density","value":"0.6","bestValue":false},{"metric":"duplicated_lines_density","value":"19.1","bestValue":false},{"metric":"test_errors","value":"0","bestValue":true},{"metric":"test_failures","value":"0","bestValue":true}]},{"id":"AYSQtNBWIoqdY8fpFmYj","key":"fga-eps-mds_2022-2-CAPJu-Interface:src","name":"src","qualifier":"DIR","path":"src","measures":[{"metric":"duplicated_lines_density","value":"3.5","bestValue":false},{"metric":"functions","value":"247"},{"metric":"security_rating","value":"1.0","bestValue":true},{"metric":"files","value":"59"},{"metric":"complexity","value":"419"},{"metric":"ncloc","value":"5076"},{"metric":"coverage","value":"72.4","bestValue":false},{"metric":"comment_lines_density","value":"0.4","bestValue":false}]},{"id":"AYSQtNBVIoqdY8fpFmYD","key":"fga-eps-mds_2022-2-CAPJu-Interface:src/pages/Stages","name":"Stages","qualifier":"DIR","path":"src/pages/Stages","measures":[{"metric":"duplicated_lines_density","value":"0.0","bestValue":true},{"metric":"functions","value":"13"},{"metric":"security_rating","value":"1.0","bestValue":true},{"metric":"files","value":"2"},{"metric":"complexity","value":"22"},{"metric":"ncloc","value":"273"},{"metric":"coverage","value":"57.7","bestValue":false},{"metric":"comment_lines_density","value":"0.0","bestValue":false}]},{"id":"AYSQtNBVIoqdY8fpFmYB","key":"fga-eps-mds_2022-2-CAPJu-Interface:src/pages/Stages/Stages.jsx","name":"Stages.jsx","qualifier":"FIL","path":"src/pages/Stages/Stages.jsx","language":"js","measures":[{"metric":"functions","value":"13"},{"metric":"security_rating","value":"1.0","bestValue":true},{"metric":"files","value":"1"},{"metric":"complexity","value":"22"},{"metric":"ncloc","value":"178"},{"metric":"coverage","value":"53.1","bestValue":false},{"metric":"comment_lines_density","value":"0.0","bestValue":false},{"metric":"test_errors","value":"0","bestValue":true},{"metric":"duplicated_lines_density","value":"0.0","bestValue":true},{"metric":"test_failures","value":"0","bestValue":true}]},{"id":"AYSQtNBVIoqdY8fpFmXW","key":"fga-eps-mds_2022-2-CAPJu-Interface:src/components/StagesInFlow","name":"StagesInFlow","qualifier":"DIR","path":"src/components/StagesInFlow","measures":[{"metric":"duplicated_lines_density","value":"0.0","bestValue":true},{"metric":"functions","value":"5"},{"metric":"security_rating","value":"1.0","bestValue":true},{"metric":"files","value":"2"},{"metric":"complexity","value":"6"},{"metric":"ncloc","value":"62"},{"metric":"coverage","value":"53.3","bestValue":false},{"metric":"comment_lines_density","value":"0.0","bestValue":false}]},{"id":"AYSQtNBVIoqdY8fpFmXV","key":"fga-eps-mds_2022-2-CAPJu-Interface:src/components/StagesInFlow/StagesInFlow.jsx","name":"StagesInFlow.jsx","qualifier":"FIL","path":"src/components/StagesInFlow/StagesInFlow.jsx","language":"js","measures":[{"metric":"functions","value":"5"},{"metric":"security_rating","value":"1.0","bestValue":true},{"metric":"files","value":"1"},{"metric":"complexity","value":"6"},{"metric":"ncloc","value":"37"},{"metric":"coverage","value":"41.7","bestValue":false},{"metric":"comment_lines_density","value":"0.0","bestValue":false},{"metric":"test_errors","value":"0","bestValue":true},{"metric":"duplicated_lines_density","value":"0.0","bestValue":true},{"metric":"test_failures","value":"0","bestValue":true}]},{"id":"AYSQtNBWIoqdY8fpFmYh","key":"fga-eps-mds_2022-2-CAPJu-Interface:src/styles.js","name":"styles.js","qualifier":"FIL","path":"src/styles.js","language":"js","measures":[{"metric":"complexity","value":"0"},{"metric":"functions","value":"0"},{"metric":"ncloc","value":"17"},{"metric":"coverage","value":"100.0","bestValue":true},{"metric":"security_rating","value":"1.0","bestValue":true},{"metric":"comment_lines_density","value":"0.0","bestValue":false},{"metric":"files","value":"1"},{"metric":"test_errors","value":"0","bestValue":true},{"metric":"duplicated_lines_density","value":"0.0","bestValue":true},{"metric":"test_failures","value":"0","bestValue":true}]},{"id":"AYSQtNBVIoqdY8fpFmXG","key":"fga-eps-mds_2022-2-CAPJu-Interface:src/components/Button/styles.js","name":"styles.js","qualifier":"FIL","path":"src/components/Button/styles.js","language":"js","measures":[{"metric":"complexity","value":"7"},{"metric":"functions","value":"4"},{"metric":"ncloc","value":"71"},{"metric":"coverage","value":"100.0","bestValue":true},{"metric":"security_rating","value":"1.0","bestValue":true},{"metric":"comment_lines_density","value":"0.0","bestValue":false},{"metric":"files","value":"1"},{"metric":"test_errors","value":"0","bestValue":true},{"metric":"duplicated_lines_density","value":"0.0","bestValue":true},{"metric":"test_failures","value":"0","bestValue":true}]},{"id":"AYSQtNBVIoqdY8fpFmXK","key":"fga-eps-mds_2022-2-CAPJu-Interface:src/components/ModalBody/styles.js","name":"styles.js","qualifier":"FIL","path":"src/components/ModalBody/styles.js","language":"js","measures":[{"metric":"complexity","value":"0"},{"metric":"functions","value":"0"},{"metric":"ncloc","value":"12"},{"metric":"coverage","value":"100.0","bestValue":true},{"metric":"security_rating","value":"1.0","bestValue":true},{"metric":"comment_lines_density","value":"0.0","bestValue":false},{"metric":"files","value":"1"},{"metric":"test_errors","value":"0","bestValue":true},{"metric":"duplicated_lines_density","value":"0.0","bestValue":true},{"metric":"test_failures","value":"0","bestValue":true}]},{"id":"AYSQtNBVIoqdY8fpFmXM","key":"fga-eps-mds_2022-2-CAPJu-Interface:src/components/SideBar/styles.js","name":"styles.js","qualifier":"FIL","path":"src/components/SideBar/styles.js","language":"js","measures":[{"metric":"complexity","value":"0"},{"metric":"functions","value":"0"},{"metric":"ncloc","value":"64"},{"metric":"coverage","value":"100.0","bestValue":true},{"metric":"security_rating","value":"1.0","bestValue":true},{"metric":"comment_lines_density","value":"0.0","bestValue":false},{"metric":"files","value":"1"},{"metric":"test_errors","value":"0","bestValue":true},{"metric":"duplicated_lines_density","value":"0.0","bestValue":true},{"metric":"test_failures","value":"0","bestValue":true}]},{"id":"AYSQtNBVIoqdY8fpFmXR","key":"fga-eps-mds_2022-2-CAPJu-Interface:src/components/TextInput/styles.js","name":"styles.js","qualifier":"FIL","path":"src/components/TextInput/styles.js","language":"js","measures":[{"metric":"complexity","value":"0"},{"metric":"functions","value":"0"},{"metric":"ncloc","value":"17"},{"metric":"coverage","value":"100.0","bestValue":true},{"metric":"security_rating","value":"1.0","bestValue":true},{"metric":"comment_lines_density","value":"0.0","bestValue":false},{"metric":"files","value":"1"},{"metric":"test_errors","value":"0","bestValue":true},{"metric":"duplicated_lines_density","value":"0.0","bestValue":true},{"metric":"test_failures","value":"0","bestValue":true}]},{"id":"AYSQtNBVIoqdY8fpFmXU","key":"fga-eps-mds_2022-2-CAPJu-Interface:src/components/StagesInFlow/styles.js","name":"styles.js","qualifier":"FIL","path":"src/components/StagesInFlow/styles.js","language":"js","measures":[{"metric":"complexity","value":"0"},{"metric":"functions","value":"0"},{"metric":"ncloc","value":"25"},{"metric":"coverage","value":"100.0","bestValue":true},{"metric":"security_rating","value":"1.0","bestValue":true},{"metric":"comment_lines_density","value":"0.0","bestValue":false},{"metric":"files","value":"1"},{"metric":"test_errors","value":"0","bestValue":true},{"metric":"duplicated_lines_density","value":"0.0","bestValue":true},{"metric":"test_failures","value":"0","bestValue":true}]},{"id":"AYSQtNBVIoqdY8fpFmXY","key":"fga-eps-mds_2022-2-CAPJu-Interface:src/components/ModalHeader/styles.js","name":"styles.js","qualifier":"FIL","path":"src/components/ModalHeader/styles.js","language":"js","measures":[{"metric":"complexity","value":"0"},{"metric":"functions","value":"0"},{"metric":"ncloc","value":"33"},{"metric":"coverage","value":"100.0","bestValue":true},{"metric":"security_rating","value":"1.0","bestValue":true},{"metric":"comment_lines_density","value":"0.0","bestValue":false},{"metric":"files","value":"1"},{"metric":"test_errors","value":"0","bestValue":true},{"metric":"duplicated_lines_density","value":"0.0","bestValue":true},{"metric":"test_failures","value":"0","bestValue":true}]},{"id":"AYSQtNBVIoqdY8fpFmXc","key":"fga-eps-mds_2022-2-CAPJu-Interface:src/components/FlowViewer/styles.js","name":"styles.js","qualifier":"FIL","path":"src/components/FlowViewer/styles.js","language":"js","measures":[{"metric":"complexity","value":"0"},{"metric":"functions","value":"0"},{"metric":"ncloc","value":"37"},{"metric":"coverage","value":"100.0","bestValue":true},{"metric":"security_rating","value":"1.0","bestValue":true},{"metric":"comment_lines_density","value":"0.0","bestValue":false},{"metric":"files","value":"1"},{"metric":"test_errors","value":"0","bestValue":true},{"metric":"duplicated_lines_density","value":"0.0","bestValue":true},{"metric":"test_failures","value":"0","bestValue":true}]},{"id":"AYSQtNBVIoqdY8fpFmXf","key":"fga-eps-mds_2022-2-CAPJu-Interface:src/components/AddStageInFlow/styles.js","name":"styles.js","qualifier":"FIL","path":"src/components/AddStageInFlow/styles.js","language":"js","measures":[{"metric":"complexity","value":"0"},{"metric":"functions","value":"0"},{"metric":"ncloc","value":"16"},{"metric":"coverage","value":"100.0","bestValue":true},{"metric":"security_rating","value":"1.0","bestValue":true},{"metric":"comment_lines_density","value":"0.0","bestValue":false},{"metric":"files","value":"1"},{"metric":"test_errors","value":"0","bestValue":true},{"metric":"duplicated_lines_density","value":"0.0","bestValue":true},{"metric":"test_failures","value":"0","bestValue":true}]},{"id":"AYWhUJA5qQu-3RSfafYk","key":"fga-eps-mds_2022-2-CAPJu-Interface:src/components/BackButton/styles.js","name":"styles.js","qualifier":"FIL","path":"src/components/BackButton/styles.js","language":"js","measures":[{"metric":"complexity","value":"1"},{"metric":"functions","value":"1"},{"metric":"ncloc","value":"10"},{"metric":"coverage","value":"100.0","bestValue":true},{"metric":"security_rating","value":"1.0","bestValue":true},{"metric":"comment_lines_density","value":"0.0","bestValue":false},{"metric":"files","value":"1"},{"metric":"test_errors","value":"0","bestValue":true},{"metric":"duplicated_lines_density","value":"0.0","bestValue":true},{"metric":"test_failures","value":"0","bestValue":true}]},{"id":"AYSQtNBVIoqdY8fpFmXy","key":"fga-eps-mds_2022-2-CAPJu-Interface:src/pages/Flows/styles.js","name":"styles.js","qualifier":"FIL","path":"src/pages/Flows/styles.js","language":"js","measures":[{"metric":"complexity","value":"0"},{"metric":"functions","value":"0"},{"metric":"ncloc","value":"221"},{"metric":"coverage","value":"100.0","bestValue":true},{"metric":"security_rating","value":"1.0","bestValue":true},{"metric":"comment_lines_density","value":"0.0","bestValue":false},{"metric":"files","value":"1"},{"metric":"test_errors","value":"0","bestValue":true},{"metric":"duplicated_lines_density","value":"0.0","bestValue":true},{"metric":"test_failures","value":"0","bestValue":true}]},{"id":"AYSQtNBVIoqdY8fpFmX5","key":"fga-eps-mds_2022-2-CAPJu-Interface:src/pages/Unidades/styles.js","name":"styles.js","qualifier":"FIL","path":"src/pages/Unidades/styles.js","language":"js","measures":[{"metric":"complexity","value":"0"},{"metric":"functions","value":"0"},{"metric":"ncloc","value":"96"},{"metric":"coverage","value":"100.0","bestValue":true},{"metric":"security_rating","value":"1.0","bestValue":true},{"metric":"comment_lines_density","value":"0.0","bestValue":false},{"metric":"files","value":"1"},{"metric":"test_errors","value":"0","bestValue":true},{"metric":"duplicated_lines_density","value":"0.0","bestValue":true},{"metric":"test_failures","value":"0","bestValue":true}]},{"id":"AYSQtNBVIoqdY8fpFmX7","key":"fga-eps-mds_2022-2-CAPJu-Interface:src/pages/ShowProcess/styles.js","name":"styles.js","qualifier":"FIL","path":"src/pages/ShowProcess/styles.js","language":"js","measures":[{"metric":"complexity","value":"0"},{"metric":"functions","value":"0"},{"metric":"ncloc","value":"49"},{"metric":"coverage","value":"100.0","bestValue":true},{"metric":"security_rating","value":"1.0","bestValue":true},{"metric":"comment_lines_density","value":"0.0","bestValue":false},{"metric":"files","value":"1"},{"metric":"test_errors","value":"0","bestValue":true},{"metric":"duplicated_lines_density","value":"0.0","bestValue":true},{"metric":"test_failures","value":"0","bestValue":true}]},{"id":"AYSQtNBVIoqdY8fpFmXj","key":"fga-eps-mds_2022-2-CAPJu-Interface:src/pages/Login/styles.js","name":"styles.js","qualifier":"FIL","path":"src/pages/Login/styles.js","language":"js","measures":[{"metric":"complexity","value":"3"},{"metric":"functions","value":"2"},{"metric":"ncloc","value":"55"},{"metric":"coverage","value":"100.0","bestValue":true},{"metric":"security_rating","value":"1.0","bestValue":true},{"metric":"comment_lines_density","value":"0.0","bestValue":false},{"metric":"files","value":"1"},{"metric":"test_errors","value":"0","bestValue":true},{"metric":"duplicated_lines_density","value":"0.0","bestValue":true},{"metric":"test_failures","value":"0","bestValue":true}]},{"id":"AYSQtNBVIoqdY8fpFmXm","key":"fga-eps-mds_2022-2-CAPJu-Interface:src/pages/EditAccountEmail/styles.js","name":"styles.js","qualifier":"FIL","path":"src/pages/EditAccountEmail/styles.js","language":"js","measures":[{"metric":"complexity","value":"0"},{"metric":"functions","value":"0"},{"metric":"ncloc","value":"44"},{"metric":"coverage","value":"100.0","bestValue":true},{"metric":"security_rating","value":"1.0","bestValue":true},{"metric":"comment_lines_density","value":"0.0","bestValue":false},{"metric":"files","value":"1"},{"metric":"test_errors","value":"0","bestValue":true},{"metric":"duplicated_lines_density","value":"0.0","bestValue":true},{"metric":"test_failures","value":"0","bestValue":true}]},{"id":"AYSQtNBVIoqdY8fpFmXq","key":"fga-eps-mds_2022-2-CAPJu-Interface:src/pages/EditAccountPassword/styles.js","name":"styles.js","qualifier":"FIL","path":"src/pages/EditAccountPassword/styles.js","language":"js","measures":[{"metric":"complexity","value":"0"},{"metric":"functions","value":"0"},{"metric":"ncloc","value":"44"},{"metric":"coverage","value":"100.0","bestValue":true},{"metric":"security_rating","value":"1.0","bestValue":true},{"metric":"comment_lines_density","value":"0.0","bestValue":false},{"metric":"files","value":"1"},{"metric":"test_errors","value":"0","bestValue":true},{"metric":"duplicated_lines_density","value":"0.0","bestValue":true},{"metric":"test_failures","value":"0","bestValue":true}]},{"id":"AYSQtNBVIoqdY8fpFmXs","key":"fga-eps-mds_2022-2-CAPJu-Interface:src/pages/Processes/styles.js","name":"styles.js","qualifier":"FIL","path":"src/pages/Processes/styles.js","language":"js","measures":[{"metric":"complexity","value":"0"},{"metric":"functions","value":"0"},{"metric":"ncloc","value":"187"},{"metric":"coverage","value":"100.0","bestValue":true},{"metric":"security_rating","value":"1.0","bestValue":true},{"metric":"comment_lines_density","value":"0.0","bestValue":false},{"metric":"files","value":"1"},{"metric":"test_errors","value":"0","bestValue":true},{"metric":"duplicated_lines_density","value":"0.0","bestValue":true},{"metric":"test_failures","value":"0","bestValue":true}]},{"id":"AYSQtNBVIoqdY8fpFmXw","key":"fga-eps-mds_2022-2-CAPJu-Interface:src/pages/Recovery/styles.js","name":"styles.js","qualifier":"FIL","path":"src/pages/Recovery/styles.js","language":"js","measures":[{"metric":"complexity","value":"3"},{"metric":"functions","value":"2"},{"metric":"ncloc","value":"43"},{"metric":"coverage","value":"62.5","bestValue":false},{"metric":"security_rating","value":"1.0","bestValue":true},{"metric":"comment_lines_density","value":"0.0","bestValue":false},{"metric":"files","value":"1"},{"metric":"test_errors","value":"0","bestValue":true},{"metric":"duplicated_lines_density","value":"0.0","bestValue":true},{"metric":"test_failures","value":"0","bestValue":true}]},{"id":"AYSQtNBVIoqdY8fpFmYC","key":"fga-eps-mds_2022-2-CAPJu-Interface:src/pages/Stages/styles.js","name":"styles.js","qualifier":"FIL","path":"src/pages/Stages/styles.js","language":"js","measures":[{"metric":"complexity","value":"0"},{"metric":"functions","value":"0"},{"metric":"ncloc","value":"95"},{"metric":"coverage","value":"100.0","bestValue":true},{"metric":"security_rating","value":"1.0","bestValue":true},{"metric":"comment_lines_density","value":"0.0","bestValue":false},{"metric":"files","value":"1"},{"metric":"test_errors","value":"0","bestValue":true},{"metric":"duplicated_lines_density","value":"0.0","bestValue":true},{"metric":"test_failures","value":"0","bestValue":true}]},{"id":"AYSQtNBWIoqdY8fpFmYI","key":"fga-eps-mds_2022-2-CAPJu-Interface:src/pages/SolicitacoesCadastro/styles.js","name":"styles.js","qualifier":"FIL","path":"src/pages/SolicitacoesCadastro/styles.js","language":"js","measures":[{"metric":"complexity","value":"0"},{"metric":"functions","value":"0"},{"metric":"ncloc","value":"74"},{"metric":"coverage","value":"100.0","bestValue":true},{"metric":"security_rating","value":"1.0","bestValue":true},{"metric":"comment_lines_density","value":"0.0","bestValue":false},{"metric":"files","value":"1"},{"metric":"test_errors","value":"0","bestValue":true},{"metric":"duplicated_lines_density","value":"0.0","bestValue":true},{"metric":"test_failures","value":"0","bestValue":true}]},{"id":"AYSQtNBWIoqdY8fpFmYK","key":"fga-eps-mds_2022-2-CAPJu-Interface:src/pages/EditAccount/styles.js","name":"styles.js","qualifier":"FIL","path":"src/pages/EditAccount/styles.js","language":"js","measures":[{"metric":"complexity","value":"0"},{"metric":"functions","value":"0"},{"metric":"ncloc","value":"36"},{"metric":"coverage","value":"100.0","bestValue":true},{"metric":"security_rating","value":"1.0","bestValue":true},{"metric":"comment_lines_density","value":"0.0","bestValue":false},{"metric":"files","value":"1"},{"metric":"test_errors","value":"0","bestValue":true},{"metric":"duplicated_lines_density","value":"0.0","bestValue":true},{"metric":"test_failures","value":"0","bestValue":true}]},{"id":"AYSQtNBVIoqdY8fpFmX_","key":"fga-eps-mds_2022-2-CAPJu-Interface:src/pages/AccessProfile/sytles.js","name":"sytles.js","qualifier":"FIL","path":"src/pages/AccessProfile/sytles.js","language":"js","measures":[{"metric":"complexity","value":"0"},{"metric":"functions","value":"0"},{"metric":"ncloc","value":"78"},{"metric":"coverage","value":"100.0","bestValue":true},{"metric":"security_rating","value":"1.0","bestValue":true},{"metric":"comment_lines_density","value":"0.0","bestValue":false},{"metric":"files","value":"1"},{"metric":"test_errors","value":"0","bestValue":true},{"metric":"duplicated_lines_density","value":"0.0","bestValue":true},{"metric":"test_failures","value":"0","bestValue":true}]},{"id":"AYWhUJA5qQu-3RSfafYg","key":"fga-eps-mds_2022-2-CAPJu-Interface:src/components/Tables/Table.jsx","name":"Table.jsx","qualifier":"FIL","path":"src/components/Tables/Table.jsx","language":"js","measures":[{"metric":"functions","value":"6"},{"metric":"security_rating","value":"1.0","bestValue":true},{"metric":"files","value":"1"},{"metric":"complexity","value":"7"},{"metric":"ncloc","value":"71"},{"metric":"coverage","value":"100.0","bestValue":true},{"metric":"comment_lines_density","value":"0.0","bestValue":false},{"metric":"test_errors","value":"0","bestValue":true},{"metric":"duplicated_lines_density","value":"0.0","bestValue":true},{"metric":"test_failures","value":"0","bestValue":true}]},{"id":"AYWhUJA5qQu-3RSfafYi","key":"fga-eps-mds_2022-2-CAPJu-Interface:src/components/Tables","name":"Tables","qualifier":"DIR","path":"src/components/Tables","measures":[{"metric":"duplicated_lines_density","value":"0.0","bestValue":true},{"metric":"functions","value":"6"},{"metric":"security_rating","value":"1.0","bestValue":true},{"metric":"files","value":"2"},{"metric":"complexity","value":"7"},{"metric":"ncloc","value":"127"},{"metric":"coverage","value":"100.0","bestValue":true},{"metric":"comment_lines_density","value":"0.0","bestValue":false}]},{"id":"AYWhUJA5qQu-3RSfafYh","key":"fga-eps-mds_2022-2-CAPJu-Interface:src/components/Tables/TableStyle.js","name":"TableStyle.js","qualifier":"FIL","path":"src/components/Tables/TableStyle.js","language":"js","measures":[{"metric":"complexity","value":"0"},{"metric":"functions","value":"0"},{"metric":"ncloc","value":"56"},{"metric":"coverage","value":"100.0","bestValue":true},{"metric":"security_rating","value":"1.0","bestValue":true},{"metric":"comment_lines_density","value":"0.0","bestValue":false},{"metric":"files","value":"1"},{"metric":"test_errors","value":"0","bestValue":true},{"metric":"duplicated_lines_density","value":"0.0","bestValue":true},{"metric":"test_failures","value":"0","bestValue":true}]},{"id":"AYSQtNBWIoqdY8fpFmYW","key":"fga-eps-mds_2022-2-CAPJu-Interface:src/__tests__/test_acceptRequest.js","name":"test_acceptRequest.js","qualifier":"UTS","path":"src/__tests__/test_acceptRequest.js","language":"js","measures":[{"metric":"security_rating","value":"1.0","bestValue":true},{"metric":"test_errors","value":"0","bestValue":true},{"metric":"duplicated_lines_density","value":"0.0","bestValue":true},{"metric":"test_failures","value":"0","bestValue":true}]},{"id":"AYWhUJA5qQu-3RSfafYm","key":"fga-eps-mds_2022-2-CAPJu-Interface:src/__tests__/test_app.js","name":"test_app.js","qualifier":"UTS","path":"src/__tests__/test_app.js","language":"js","measures":[{"metric":"security_rating","value":"1.0","bestValue":true},{"metric":"test_errors","value":"0","bestValue":true},{"metric":"duplicated_lines_density","value":"0.0","bestValue":true},{"metric":"test_failures","value":"0","bestValue":true}]},{"id":"AYSQtNBWIoqdY8fpFmYX","key":"fga-eps-mds_2022-2-CAPJu-Interface:src/__tests__/test_editAccount.js","name":"test_editAccount.js","qualifier":"UTS","path":"src/__tests__/test_editAccount.js","language":"js","measures":[{"metric":"security_rating","value":"1.0","bestValue":true},{"metric":"test_errors","value":"0","bestValue":true},{"metric":"duplicated_lines_density","value":"0.0","bestValue":true},{"metric":"test_failures","value":"0","bestValue":true}]},{"id":"AYSQtNBWIoqdY8fpFmYa","key":"fga-eps-mds_2022-2-CAPJu-Interface:src/__tests__/test_flows.js","name":"test_flows.js","qualifier":"UTS","path":"src/__tests__/test_flows.js","language":"js","measures":[{"metric":"security_rating","value":"1.0","bestValue":true},{"metric":"test_errors","value":"0","bestValue":true},{"metric":"duplicated_lines_density","value":"0.0","bestValue":true},{"metric":"test_failures","value":"0","bestValue":true}]},{"id":"AYSQtNBWIoqdY8fpFmYU","key":"fga-eps-mds_2022-2-CAPJu-Interface:src/__tests__/test_login.js","name":"test_login.js","qualifier":"UTS","path":"src/__tests__/test_login.js","language":"js","measures":[{"metric":"security_rating","value":"1.0","bestValue":true},{"metric":"test_errors","value":"0","bestValue":true},{"metric":"duplicated_lines_density","value":"0.0","bestValue":true},{"metric":"test_failures","value":"0","bestValue":true}]},{"id":"AYSQtNBWIoqdY8fpFmYT","key":"fga-eps-mds_2022-2-CAPJu-Interface:src/__tests__/test_process.js","name":"test_process.js","qualifier":"UTS","path":"src/__tests__/test_process.js","language":"js","measures":[{"metric":"security_rating","value":"1.0","bestValue":true},{"metric":"test_errors","value":"0","bestValue":true},{"metric":"duplicated_lines_density","value":"0.0","bestValue":true},{"metric":"test_failures","value":"0","bestValue":true}]},{"id":"AYSQtNBWIoqdY8fpFmYS","key":"fga-eps-mds_2022-2-CAPJu-Interface:src/__tests__/test_register.js","name":"test_register.js","qualifier":"UTS","path":"src/__tests__/test_register.js","language":"js","measures":[{"metric":"security_rating","value":"1.0","bestValue":true},{"metric":"test_errors","value":"0","bestValue":true},{"metric":"duplicated_lines_density","value":"0.0","bestValue":true},{"metric":"test_failures","value":"0","bestValue":true}]},{"id":"AYSQtNBWIoqdY8fpFmYY","key":"fga-eps-mds_2022-2-CAPJu-Interface:src/__tests__/test_roles.js","name":"test_roles.js","qualifier":"UTS","path":"src/__tests__/test_roles.js","language":"js","measures":[{"metric":"security_rating","value":"1.0","bestValue":true},{"metric":"test_errors","value":"0","bestValue":true},{"metric":"duplicated_lines_density","value":"0.0","bestValue":true},{"metric":"test_failures","value":"0","bestValue":true}]},{"id":"AYSQtNBWIoqdY8fpFmYZ","key":"fga-eps-mds_2022-2-CAPJu-Interface:src/__tests__/test_searchProcesses.js","name":"test_searchProcesses.js","qualifier":"UTS","path":"src/__tests__/test_searchProcesses.js","language":"js","measures":[{"metric":"security_rating","value":"1.0","bestValue":true},{"metric":"test_errors","value":"0","bestValue":true},{"metric":"duplicated_lines_density","value":"0.0","bestValue":true},{"metric":"test_failures","value":"0","bestValue":true}]},{"id":"AYWhUJA5qQu-3RSfafYn","key":"fga-eps-mds_2022-2-CAPJu-Interface:src/__tests__/test_sideBar.js","name":"test_sideBar.js","qualifier":"UTS","path":"src/__tests__/test_sideBar.js","language":"js","measures":[{"metric":"security_rating","value":"1.0","bestValue":true},{"metric":"test_errors","value":"0","bestValue":true},{"metric":"duplicated_lines_density","value":"0.0","bestValue":true},{"metric":"test_failures","value":"0","bestValue":true}]},{"id":"AYSQtNBWIoqdY8fpFmYV","key":"fga-eps-mds_2022-2-CAPJu-Interface:src/__tests__/test_stage.js","name":"test_stage.js","qualifier":"UTS","path":"src/__tests__/test_stage.js","language":"js","measures":[{"metric":"security_rating","value":"1.0","bestValue":true},{"metric":"test_errors","value":"0","bestValue":true},{"metric":"duplicated_lines_density","value":"0.0","bestValue":true},{"metric":"test_failures","value":"0","bestValue":true}]},{"id":"AYWhUJA5qQu-3RSfafYo","key":"fga-eps-mds_2022-2-CAPJu-Interface:src/__tests__/test_units.js","name":"test_units.js","qualifier":"UTS","path":"src/__tests__/test_units.js","language":"js","measures":[{"metric":"security_rating","value":"1.0","bestValue":true},{"metric":"test_errors","value":"0","bestValue":true},{"metric":"duplicated_lines_density","value":"0.0","bestValue":true},{"metric":"test_failures","value":"0","bestValue":true}]},{"id":"AYSQtNBWIoqdY8fpFmYc","key":"fga-eps-mds_2022-2-CAPJu-Interface:src/testConstants.js","name":"testConstants.js","qualifier":"FIL","path":"src/testConstants.js","language":"js","measures":[{"metric":"files","value":"1"},{"metric":"ncloc","value":"274"},{"metric":"coverage","value":"100.0","bestValue":true},{"metric":"functions","value":"0"},{"metric":"complexity","value":"0"},{"metric":"security_rating","value":"1.0","bestValue":true},{"metric":"comment_lines_density","value":"0.0","bestValue":false},{"metric":"duplicated_lines_density","value":"29.2","bestValue":false},{"metric":"test_errors","value":"0","bestValue":true},{"metric":"test_failures","value":"0","bestValue":true}]},{"id":"AYSQtNBVIoqdY8fpFmXT","key":"fga-eps-mds_2022-2-CAPJu-Interface:src/components/TextInput","name":"TextInput","qualifier":"DIR","path":"src/components/TextInput","measures":[{"metric":"duplicated_lines_density","value":"0.0","bestValue":true},{"metric":"functions","value":"2"},{"metric":"security_rating","value":"1.0","bestValue":true},{"metric":"files","value":"2"},{"metric":"complexity","value":"2"},{"metric":"ncloc","value":"42"},{"metric":"coverage","value":"100.0","bestValue":true},{"metric":"comment_lines_density","value":"0.0","bestValue":false}]},{"id":"AYSQtNBVIoqdY8fpFmXS","key":"fga-eps-mds_2022-2-CAPJu-Interface:src/components/TextInput/TextInput.jsx","name":"TextInput.jsx","qualifier":"FIL","path":"src/components/TextInput/TextInput.jsx","language":"js","measures":[{"metric":"complexity","value":"2"},{"metric":"functions","value":"2"},{"metric":"ncloc","value":"25"},{"metric":"coverage","value":"100.0","bestValue":true},{"metric":"security_rating","value":"1.0","bestValue":true},{"metric":"comment_lines_density","value":"0.0","bestValue":false},{"metric":"files","value":"1"},{"metric":"test_errors","value":"0","bestValue":true},{"metric":"duplicated_lines_density","value":"0.0","bestValue":true},{"metric":"test_failures","value":"0","bestValue":true}]},{"id":"AYSQtNBVIoqdY8fpFmX6","key":"fga-eps-mds_2022-2-CAPJu-Interface:src/pages/Unidades","name":"Unidades","qualifier":"DIR","path":"src/pages/Unidades","measures":[{"metric":"duplicated_lines_density","value":"0.0","bestValue":true},{"metric":"functions","value":"20"},{"metric":"security_rating","value":"1.0","bestValue":true},{"metric":"files","value":"2"},{"metric":"complexity","value":"30"},{"metric":"ncloc","value":"334"},{"metric":"coverage","value":"79.3","bestValue":false},{"metric":"comment_lines_density","value":"0.0","bestValue":false}]},{"id":"AYSQtNBVIoqdY8fpFmX4","key":"fga-eps-mds_2022-2-CAPJu-Interface:src/pages/Unidades/Unidades.jsx","name":"Unidades.jsx","qualifier":"FIL","path":"src/pages/Unidades/Unidades.jsx","language":"js","measures":[{"metric":"functions","value":"20"},{"metric":"security_rating","value":"1.0","bestValue":true},{"metric":"files","value":"1"},{"metric":"complexity","value":"30"},{"metric":"ncloc","value":"238"},{"metric":"coverage","value":"77.5","bestValue":false},{"metric":"comment_lines_density","value":"0.0","bestValue":false},{"metric":"test_errors","value":"0","bestValue":true},{"metric":"duplicated_lines_density","value":"0.0","bestValue":true},{"metric":"test_failures","value":"0","bestValue":true}]},{"id":"AYSQtNBWIoqdY8fpFmYQ","key":"fga-eps-mds_2022-2-CAPJu-Interface:src/services/user.js","name":"user.js","qualifier":"FIL","path":"src/services/user.js","language":"js","measures":[{"metric":"complexity","value":"1"},{"metric":"functions","value":"0"},{"metric":"ncloc","value":"10"},{"metric":"coverage","value":"75.0","bestValue":false},{"metric":"security_rating","value":"1.0","bestValue":true},{"metric":"comment_lines_density","value":"0.0","bestValue":false},{"metric":"files","value":"1"},{"metric":"test_errors","value":"0","bestValue":true},{"metric":"duplicated_lines_density","value":"0.0","bestValue":true},{"metric":"test_failures","value":"0","bestValue":true}]},{"id":"AYWhUJA5qQu-3RSfafYr","key":"fga-eps-mds_2022-2-CAPJu-Interface:src/validators","name":"validators","qualifier":"DIR","path":"src/validators","measures":[{"metric":"duplicated_lines_density","value":"84.8","bestValue":false},{"metric":"functions","value":"3"},{"metric":"security_rating","value":"1.0","bestValue":true},{"metric":"files","value":"2"},{"metric":"complexity","value":"22"},{"metric":"ncloc","value":"77"},{"metric":"coverage","value":"42.6","bestValue":false},{"metric":"comment_lines_density","value":"0.0","bestValue":false}]}]}